[{
  "rating": {
    "max": 10,
    "average": 4.8,
    "stars": "25",
    "min": 0
  },
  "genres": [
    "剧情"
  ],
  "title": "半熟少女",
  "casts": [{
    "alt": "http://movie.douban.com/celebrity/1347985/",
    "avatars": {
      "small": "http://img3.doubanio.com/img/celebrity/small/BrbnU9r7uewcel_avatar_uploaded1423890664.7.jpg",
      "large": "http://img3.doubanio.com/img/celebrity/large/BrbnU9r7uewcel_avatar_uploaded1423890664.7.jpg",
      "medium": "http://img3.doubanio.com/img/celebrity/medium/BrbnU9r7uewcel_avatar_uploaded1423890664.7.jpg"
    },
    "name": "黄灿灿",
    "id": "1347985"
  }, {
    "alt": "http://movie.douban.com/celebrity/1315837/",
    "avatars": {
      "small": "http://img3.doubanio.com/img/celebrity/small/37266.jpg",
      "large": "http://img3.doubanio.com/img/celebrity/large/37266.jpg",
      "medium": "http://img3.doubanio.com/img/celebrity/medium/37266.jpg"
    },
    "name": "敖犬",
    "id": "1315837"
  }, {
    "alt": "http://movie.douban.com/celebrity/1339697/",
    "avatars": {
      "small": "http://img3.doubanio.com/img/celebrity/small/1406737170.56.jpg",
      "large": "http://img3.doubanio.com/img/celebrity/large/1406737170.56.jpg",
      "medium": "http://img3.doubanio.com/img/celebrity/medium/1406737170.56.jpg"
    },
    "name": "南笙",
    "id": "1339697"
  }],
  "collect_count": 648,
  "original_title": "半熟少女",
  "subtype": "movie",
  "directors": [{
    "alt": "http://movie.douban.com/celebrity/1274272/",
    "avatars": {
      "small": "http://img3.douban.com/img/celebrity/small/1369212463.55.jpg",
      "large": "http://img3.douban.com/img/celebrity/large/1369212463.55.jpg",
      "medium": "http://img3.douban.com/img/celebrity/medium/1369212463.55.jpg"
    },
    "name": "阿牛",
    "id": "1274272"
  }, {
    "alt": "http://movie.douban.com/celebrity/1320916/",
    "avatars": {
      "small": "http://img3.douban.com/img/celebrity/small/1454162187.92.jpg",
      "large": "http://img3.douban.com/img/celebrity/large/1454162187.92.jpg",
      "medium": "http://img3.douban.com/img/celebrity/medium/1454162187.92.jpg"
    },
    "name": "赵宇",
    "id": "1320916"
  }, {
    "alt": "http://movie.douban.com/celebrity/1340717/",
    "avatars": {
      "small": "http://img3.douban.com/img/celebrity/small/1402659545.4.jpg",
      "large": "http://img3.douban.com/img/celebrity/large/1402659545.4.jpg",
      "medium": "http://img3.douban.com/img/celebrity/medium/1402659545.4.jpg"
    },
    "name": "陈立谦",
    "id": "1340717"
  }],
  "year": "2016",
  "images": {
    "small": "http://img3.douban.com/view/movie_poster_cover/ipst/public/p2326378603.jpg",
    "large": "http://img3.douban.com/view/movie_poster_cover/lpst/public/p2326378603.jpg",
    "medium": "http://img3.douban.com/view/movie_poster_cover/spst/public/p2326378603.jpg"
  },
  "alt": "http://movie.douban.com/subject/26345159/",
  "id": "26345159"
}, {
  "rating": {
    "max": 10,
    "average": 3.4,
    "stars": "20",
    "min": 0
  },
  "genres": [
    "动作",
    "爱情",
    "武侠"
  ],
  "title": "喜乐长安",
  "casts": [{
    "alt": "http://movie.douban.com/celebrity/1339958/",
    "avatars": {
      "small": "http://img3.douban.com/img/celebrity/small/z78D12LQKVEcel_avatar_uploaded1398232275.41.jpg",
      "large": "http://img3.douban.com/img/celebrity/large/z78D12LQKVEcel_avatar_uploaded1398232275.41.jpg",
      "medium": "http://img3.douban.com/img/celebrity/medium/z78D12LQKVEcel_avatar_uploaded1398232275.41.jpg"
    },
    "name": "张天阳",
    "id": "1339958"
  }, {
    "alt": "http://movie.douban.com/celebrity/1328277/",
    "avatars": {
      "small": "http://img3.doubanio.com/img/celebrity/small/1409068232.48.jpg",
      "large": "http://img3.doubanio.com/img/celebrity/large/1409068232.48.jpg",
      "medium": "http://img3.doubanio.com/img/celebrity/medium/1409068232.48.jpg"
    },
    "name": "何泓姗",
    "id": "1328277"
  }, {
    "alt": "http://movie.douban.com/celebrity/1350240/",
    "avatars": {
      "small": "http://img3.doubanio.com/f/movie/ca527386eb8c4e325611e22dfcb04cc116d6b423/pics/movie/celebrity-default-small.png",
      "large": "http://img3.douban.com/f/movie/63acc16ca6309ef191f0378faf793d1096a3e606/pics/movie/celebrity-default-large.png",
      "medium": "http://img3.doubanio.com/f/movie/8dd0c794499fe925ae2ae89ee30cd225750457b4/pics/movie/celebrity-default-medium.png"
    },
    "name": "万仓",
    "id": "1350240"
  }],
  "collect_count": 400,
  "original_title": "喜乐长安",
  "subtype": "movie",
  "directors": [{
    "alt": "http://movie.douban.com/celebrity/1327481/",
    "avatars": {
      "small": "http://img3.douban.com/img/celebrity/small/1368521523.3.jpg",
      "large": "http://img3.douban.com/img/celebrity/large/1368521523.3.jpg",
      "medium": "http://img3.douban.com/img/celebrity/medium/1368521523.3.jpg"
    },
    "name": "竹卿",
    "id": "1327481"
  }],
  "year": "2016",
  "images": {
    "small": "http://img3.douban.com/view/movie_poster_cover/ipst/public/p2323300602.jpg",
    "large": "http://img3.douban.com/view/movie_poster_cover/lpst/public/p2323300602.jpg",
    "medium": "http://img3.douban.com/view/movie_poster_cover/spst/public/p2323300602.jpg"
  },
  "alt": "http://movie.douban.com/subject/25924268/",
  "id": "25924268"
}, {
  "rating": {
    "max": 10,
    "average": 4.7,
    "stars": "25",
    "min": 0
  },
  "genres": [
    "喜剧",
    "爱情"
  ],
  "title": "女汉子真爱公式",
  "casts": [{
    "alt": "http://movie.douban.com/celebrity/1275620/",
    "avatars": {
      "small": "http://img3.doubanio.com/img/celebrity/small/1423139667.58.jpg",
      "large": "http://img3.doubanio.com/img/celebrity/large/1423139667.58.jpg",
      "medium": "http://img3.doubanio.com/img/celebrity/medium/1423139667.58.jpg"
    },
    "name": "赵丽颖",
    "id": "1275620"
  }, {
    "alt": "http://movie.douban.com/celebrity/1031500/",
    "avatars": {
      "small": "http://img3.douban.com/img/celebrity/small/39883.jpg",
      "large": "http://img3.douban.com/img/celebrity/large/39883.jpg",
      "medium": "http://img3.douban.com/img/celebrity/medium/39883.jpg"
    },
    "name": "张翰",
    "id": "1031500"
  }, {
    "alt": "http://movie.douban.com/celebrity/1320526/",
    "avatars": {
      "small": "http://img3.doubanio.com/img/celebrity/small/49339.jpg",
      "large": "http://img3.doubanio.com/img/celebrity/large/49339.jpg",
      "medium": "http://img3.doubanio.com/img/celebrity/medium/49339.jpg"
    },
    "name": "童菲",
    "id": "1320526"
  }],
  "collect_count": 3827,
  "original_title": "女汉子真爱公式",
  "subtype": "movie",
  "directors": [{
    "alt": "http://movie.douban.com/celebrity/1352793/",
    "avatars": {
      "small": "http://img3.douban.com/img/celebrity/small/1451286288.54.jpg",
      "large": "http://img3.douban.com/img/celebrity/large/1451286288.54.jpg",
      "medium": "http://img3.douban.com/img/celebrity/medium/1451286288.54.jpg"
    },
    "name": "郭大雷",
    "id": "1352793"
  }],
  "year": "2016",
  "images": {
    "small": "http://img3.douban.com/view/movie_poster_cover/ipst/public/p2324372895.jpg",
    "large": "http://img3.douban.com/view/movie_poster_cover/lpst/public/p2324372895.jpg",
    "medium": "http://img3.douban.com/view/movie_poster_cover/spst/public/p2324372895.jpg"
  },
  "alt": "http://movie.douban.com/subject/26345736/",
  "id": "26345736"
}, {
  "rating": {
    "max": 10,
    "average": 6.8,
    "stars": "35",
    "min": 0
  },
  "genres": [
    "动作",
    "奇幻",
    "冒险"
  ],
  "title": "神战：权力之眼",
  "casts": [{
    "alt": "http://movie.douban.com/celebrity/1076051/",
    "avatars": {
      "small": "http://img3.douban.com/img/celebrity/small/1368693740.25.jpg",
      "large": "http://img3.douban.com/img/celebrity/large/1368693740.25.jpg",
      "medium": "http://img3.douban.com/img/celebrity/medium/1368693740.25.jpg"
    },
    "name": "尼古拉·科斯特-瓦尔道",
    "id": "1076051"
  }, {
    "alt": "http://movie.douban.com/celebrity/1325896/",
    "avatars": {
      "small": "http://img3.douban.com/img/celebrity/small/1410910563.02.jpg",
      "large": "http://img3.douban.com/img/celebrity/large/1410910563.02.jpg",
      "medium": "http://img3.douban.com/img/celebrity/medium/1410910563.02.jpg"
    },
    "name": "布伦顿·思韦茨",
    "id": "1325896"
  }, {
    "alt": "http://movie.douban.com/celebrity/1040500/",
    "avatars": {
      "small": "http://img3.doubanio.com/img/celebrity/small/406.jpg",
      "large": "http://img3.doubanio.com/img/celebrity/large/406.jpg",
      "medium": "http://img3.doubanio.com/img/celebrity/medium/406.jpg"
    },
    "name": "杰拉德·巴特勒",
    "id": "1040500"
  }],
  "collect_count": 14095,
  "original_title": "Gods of Egypt",
  "subtype": "movie",
  "directors": [{
    "alt": "http://movie.douban.com/celebrity/1027346/",
    "avatars": {
      "small": "http://img3.douban.com/img/celebrity/small/9385.jpg",
      "large": "http://img3.douban.com/img/celebrity/large/9385.jpg",
      "medium": "http://img3.douban.com/img/celebrity/medium/9385.jpg"
    },
    "name": "亚历克斯·普罗亚斯",
    "id": "1027346"
  }],
  "year": "2016",
  "images": {
    "small": "http://img3.douban.com/view/movie_poster_cover/ipst/public/p2324130130.jpg",
    "large": "http://img3.douban.com/view/movie_poster_cover/lpst/public/p2324130130.jpg",
    "medium": "http://img3.douban.com/view/movie_poster_cover/spst/public/p2324130130.jpg"
  },
  "alt": "http://movie.douban.com/subject/26662345/",
  "id": "26662345"
}, {
  "rating": {
    "max": 10,
    "average": 5.9,
    "stars": "30",
    "min": 0
  },
  "genres": [
    "戏曲"
  ],
  "title": "白毛女",
  "casts": [{
    "alt": "http://movie.douban.com/celebrity/1355986/",
    "avatars": {
      "small": "http://img3.doubanio.com/img/celebrity/small/1458873622.36.jpg",
      "large": "http://img3.doubanio.com/img/celebrity/large/1458873622.36.jpg",
      "medium": "http://img3.doubanio.com/img/celebrity/medium/1458873622.36.jpg"
    },
    "name": "雷佳",
    "id": "1355986"
  }, {
    "alt": "http://movie.douban.com/celebrity/1355987/",
    "avatars": {
      "small": "http://img3.douban.com/img/celebrity/small/1458873756.82.jpg",
      "large": "http://img3.douban.com/img/celebrity/large/1458873756.82.jpg",
      "medium": "http://img3.douban.com/img/celebrity/medium/1458873756.82.jpg"
    },
    "name": "张英席",
    "id": "1355987"
  }, {
    "alt": "http://movie.douban.com/celebrity/1355988/",
    "avatars": {
      "small": "http://img3.douban.com/img/celebrity/small/1458874002.75.jpg",
      "large": "http://img3.douban.com/img/celebrity/large/1458874002.75.jpg",
      "medium": "http://img3.douban.com/img/celebrity/medium/1458874002.75.jpg"
    },
    "name": "高鹏",
    "id": "1355988"
  }],
  "collect_count": 89,
  "original_title": "白毛女",
  "subtype": "movie",
  "directors": [{
    "alt": "http://movie.douban.com/celebrity/1325604/",
    "avatars": {
      "small": "http://img3.douban.com/img/celebrity/small/1355121149.54.jpg",
      "large": "http://img3.douban.com/img/celebrity/large/1355121149.54.jpg",
      "medium": "http://img3.douban.com/img/celebrity/medium/1355121149.54.jpg"
    },
    "name": "侯克明",
    "id": "1325604"
  }],
  "year": "2016",
  "images": {
    "small": "http://img3.douban.com/view/movie_poster_cover/ipst/public/p2325362155.jpg",
    "large": "http://img3.douban.com/view/movie_poster_cover/lpst/public/p2325362155.jpg",
    "medium": "http://img3.douban.com/view/movie_poster_cover/spst/public/p2325362155.jpg"
  },
  "alt": "http://movie.douban.com/subject/26708775/",
  "id": "26708775"
}]
